Workbook
Name A: #REF!
Name A: #REF!
Name A: #REF!
Name A: #REF!
Name A: #REF!
Name A: #REF!
Name A: #REF!
Name A: #REF!
Name A: #REF!
Name A: #REF!
Name A: #REF!
Name B: #REF!
Name B: #REF!
Name B: #REF!
Name B: #REF!
Name B: #REF!
Name B: #REF!
Name B: #REF!
Name B: #REF!
Name B: #REF!
Name B: #REF!
Name B: #REF!
Name FECHAINGRESO: #REF!
Name FECHAINGRESO: #REF!
Name FECHAINGRESO: #REF!
Name FECHAINGRESO: #REF!
Name FECHAINGRESO: #REF!
Name FECHAINGRESO: #REF!
Name FECHAINGRESO: #REF!
Name FECHAINGRESO: #REF!
Name FECHAINGRESO: #REF!
Name FECHAINGRESO: #REF!
Name FECHAINGRESO: #REF!
Name FECHAPAGO_MAT: #REF!
Name FECHAPAGO_MAT: #REF!
Name FECHAPAGO_MAT: #REF!
Name FECHAPAGO_MAT: #REF!
Name FECHAPAGO_MAT: #REF!
Name FECHAPAGO_MAT: #REF!
Name FECHAPAGO_MAT: #REF!
Name FECHAPAGO_MAT: #REF!
Name FECHAPAGO_MAT: #REF!
Name FECHAPAGO_MAT: #REF!
Name FECHAPAGO_MAT: #REF!
Name FECHAPAGO_MO: #REF!
Name FECHAPAGO_MO: #REF!
Name FECHAPAGO_MO: #REF!
Name FECHAPAGO_MO: #REF!
Name FECHAPAGO_MO: #REF!
Name FECHAPAGO_MO: #REF!
Name FECHAPAGO_MO: #REF!
Name FECHAPAGO_MO: #REF!
Name FECHAPAGO_MO: #REF!
Name FECHAPAGO_MO: #REF!
Name FECHAPAGO_MO: #REF!
Name GASTOSMAT: #REF!
Name GASTOSMAT: #REF!
Name GASTOSMAT: #REF!
Name GASTOSMAT: #REF!
Name GASTOSMAT: #REF!

Sheet PAGOS QUINCENALES
A1: SF - PAGOS TOTALES ALBAÑILERÍA BELTRÁN X QUINCENA
A4: MAYO | C4: JUNIO | E4: JULIO | G4: AGOSTO | I4: SEPTIEMBRE | K4: OCTUBRE | M4: NOVIEMBRE
A5: C1 | C5: C2 | E5: C3 | G5: C4 | I5: C5 | K5: C6 | M5: C7
A6: Q1 | B6: Q2 | C6: Q1 | D6: Q2 | E6: Q1 | F6: Q2 | G6: Q1 | H6: Q2 | I6: Q1 | J6: Q2 | K6: Q1 | L6: Q2 | M6: Q1 | N6: Q2
A7: =SUM('M11'!F46+'M10'!F46) -> 8101600 | B7: =SUM('M11'!G46+'M10'!G46) -> 9348000 | C7: =SUM('M11'!H46+'M10'!H46+'M08'!F46) -> 7435600 | D7: =SUM('M11'!I46+'M10'!I46+'M08'!G46) -> 9348000 | E7: =SUM('M11'!J46+'M10'!J46+'M08'!H46) -> 0 | F7: =SUM('M11'!K46+'M10'!K46+'M08'!I46) -> 0 | G7: =SUM('M11'!L46+'M10'!L46+'M08'!J46+'M07'!F46+'M05'!F46) -> 0 | H7: =SUM('M11'!M46+'M10'!M46+'M08'!K46) -> 0 | I7: =SUM('M11'!N46+'M10'!N46+'M08'!L46) -> 0 | J7: =SUM('M11'!O46+'M10'!O46+'M08'!M46) -> 0 | K7: =SUM('M11'!P46+'M10'!P46+'M08'!N46) -> 0 | L7: =SUM('M11'!Q46+'M10'!Q46+'M08'!O46) -> 0 | M7: =SUM('M11'!R46+'M10'!R46+'M08'!P46) -> 0 | N7: =SUM('M11'!S46+'M10'!S46+'M08'!Q46) -> 0
A9: DICIEMBRE | C9: ENERO | E9: FEBRERO | G9: MARZO | I9: ABRIL | K9: MAYO | M9: JUNIO
A10: C8 | C10: C9 | E10: C10 | G10: C11 | I10: C12 | K10: C13 | M10: C14
A11: Q1 | B11: Q2 | C11: Q1 | D11: Q2 | E11: Q1 | F11: Q2 | G11: Q3 | H11: Q4 | I11: Q5 | J11: Q6 | K11: Q7 | L11: Q8 | M11: Q9 | N11: Q10
A12: =SUM('M11'!T46+'M10'!T46+'M08'!R46) -> 0 | B12: =SUM('M11'!U46+'M10'!U46+'M08'!S46) -> 0 | C12: =SUM('M11'!V46+'M10'!V46+'M08'!T46) -> 0 | D12: =SUM('M11'!W46+'M10'!W46+'M08'!U46) -> 0 | E12: =SUM('M11'!X46+'M10'!X46+'M08'!V46) -> 0 | F12: =SUM('M11'!Y46+'M10'!Y46+'M08'!W46) -> 0 | G12: =SUM('M11'!Z46+'M10'!Z46+'M08'!X46) -> 0 | H12: =SUM('M11'!AA46+'M10'!AA46+'M08'!Y46) -> 0 | ... N12: =SUM('M11'!AG46+'M10'!AG46+'M08'!AE46) -> 0
A14: TOTAL PAGADO | C14: =SUM(A7:N7,A12:N12) -> 34233200

Sheet CASH FLOW con anticipo
B1: SF - ALBAÑILERÍA BELTRÁN
A2: MES BASE ACTUALIZACIÓN | C2: 46113
A3: MONTO DE OBRA INICIAL | C3: 35000000
A4: ANTICIPO | C4: 3840000 | D4: =C4/C3 -> 0.10971429
F5: MAYO | H5: JUNIO | J5: JULIO | L5: AGOSTO | N5: SEPTIEMBRE | P5: OCTUBRE | R5: NOVIEMBRE | T5: DICIEMBRE | V5: ENERO | X5: FEBRERO | Z5: MARZO | AB5: ABRIL | AD5: MAYO | AF5: JUNIO
A6: ITEM | B6: DESCRIPCIÓN | C6: % ITEM | D6: MONTO TOTAL | E6: FINALIZADO | F6: C1 | H6: C2 | J6: C3 | L6: C4 | N6: C5 | P6: C6 | R6: C7 | T6: C8 | V6: C9 | X6: C10 | Z6: C11 | AB6: C12 | AD6: C13 | AF6: C14
A7: 1 | B7: MAMPOSTERIA | C7: =SUM(C8:C9) -> 0.17 | D7: =C7*C3 -> 5950000 | F7: Q1 | G7: Q2 | H7: Q1 | I7: Q2 | J7: Q1 | K7: Q2 | L7: Q1 | M7: Q2 | N7: Q1 | O7: Q2 | P7: Q1 | Q7: Q2 | R7: Q1 | S7: Q2 | T7: Q1 | U7: Q2 | V7: Q1 | W7: Q2 | X7: Q1 | Y7: Q2 | Z7: Q3 | AA7: Q4 | AB7: Q5 | AC7: Q6 | AD7: Q7 | AE7: Q8 | AF7: Q9 | AG7: Q10
A8: 1 | B8: Módulo completo Brimax | C8: 0.12 | E8: =SUM(F8:AG8) -> 0.12 | F8: 0.1 | G8: 0.02
A9: 2 | B9: Contenciones de acceso a P.B. (Promedio 5m x 0,7h con viga de fundacion) | C9: 0.05 | E9: =SUM(F9:AG9) -> 0.05 | J9: 0.05
A11: 2 | B11: REVOQUES | C11: =SUM(C12) -> 0.15 | D11: =C11*C3 -> 5250000
A12: 1 | B12: Módulo completo | C12: 0.15 | E12: =SUM(F12:AG12) -> 0.15 | I12: 0.075 | J12: 0.075
A14: 3 | B14: AISLACIONES | C14: =SUM(C15:C16) -> 0.12 | D14: =C14*C3 -> 4200000
A15: 1 | B15: Webertec (Exterior + duchas) | C15: 0.06 | E15: =SUM(F15:AG15) -> 0.06 | F15: 0.03 | G15: 0.03
A16: 2 | B16: Exterior (Memb. líquida - incluye cantero dormi) | C16: 0.06 | E16: =SUM(F16:AG16) -> 0.06 | I16: 0.03 | K16: 0.03
A18: 4 | B18: CONTRAPISOS | C18: =SUM(C19:C20) -> 0.18 | D18: =C18*C3 -> 6300000
A19: 1 | B19: Interior duplex | C19: 0.12 | E19: =SUM(F19:AG19) -> 0.12 | G19: 0.03 | H19: 0.09
A20: 2 | B20: Exterior | C20: 0.06 | E20: =SUM(F20:AG20) -> 0.06 | G20: 0.03 | H20: 0.03
A22: 5 | B22: CARPETAS | C22: =SUM(C23:C23) -> 0.06 | D22: =C22*C3 -> 2100000
A23: 1 | B23: Exterior | C23: 0.06 | E23: =SUM(F23:AG23) -> 0.06 | I23: 0.06
A25: 6 | B25: HORMIGÓN | C25: =SUM(C26:C30) -> 0.16 | D25: =C25*C3 -> 5600000
A26: 1 | B26: Banco Tromen | C26: 0.05 | E26: =SUM(F26:AG26) -> 0.05 | J26: 0.05
A27: 2 | B27: Parrilla | C27: 0.05 | E27: =SUM(F27:AG27) -> 0.05 | G27: 0.05
A28: 3 | B28: Banquinas (Parrilla + bauleras) | C28: 0.02 | E28: =SUM(F28:AG28) -> 0.02 | I28: 0.02
A29: 4 | B29: Losetones acceso vehicular | C29: 0.02 | E29: =SUM(F29:AG29) -> 0.02 | K29: 0.02
A30: 5 | B30: Losetones acceso peatonal | C30: 0.02 | E30: =SUM(F30:AG30) -> 0.02 | K30: 0.02
A32: 7 | B32: COLOCACIÓN | C32: =SUM(C33:C36) -> 0.16 | D32: =C32*C3 -> 5600000
A33: 1 | B33: Pisos | C33: 0.06 | E33: =SUM(F33:AG33) -> 0.06 | R33: 0.06
A34: 2 | B34: Baños | C34: 0.06 | E34: =SUM(F34:AG34) -> 0.06 | S34: 0.06
A35: 3 | B35: Cocina | C35: 0.03 | E35: =SUM(F35:AG35) -> 0.03 | T35: 0.03
A36: 4 | B36: Refractarios parrilla | C36: 0.01 | E36: =SUM(F36:AG36) -> 0.01 | T36: 0.01
B38: TOTAL OBRA | C38: =SUM(C7+C11+C14+C18+C22+C25+C32) -> 1 | E38: =SUM(F38:AG38) -> 1 | F38: =SUM(F8:F37) -> 0.13 | G38: =SUM(G8:G37) -> 0.16 | H38: =SUM(H8:H37) -> 0.12 | I38: =SUM(I8:I37) -> 0.185 | J38: =SUM(J8:J37) -> 0.175 | K38: =SUM(K8:K37) -> 0.07 | L38: =SUM(L8:L37) -> 0 | M38: =SUM(M8:M37) -> 0 | ... AG38: =SUM(AG8:AG37) -> 0
A40: AJUSTE | F40: 0 | G40: 0 | H40: 0 | I40: 0 | J40: 0 | K40: 0 | L40: 0 | M40: 0 | N40: 0 | O40: 0 | P40: 0 | Q40: 0 | R40: 0 | S40: 0 | T40: 0 | U40: 0 | V40: 0 | W40: 0 | X40: 0 | Y40: 0 | Z40: 0 | AA40: 0 | AB40: 0 | AC40: 0 | AD40: 0 | AE40: 0 | AF40: 0 | AG40: 0
A42: MONTO DE OBRA ACTUALIZADO | F42: =C3+(C3*F40) -> 35000000 | G42: =F42+(F42*G40) -> 35000000 | H42: =G42+(G42*H40) -> 35000000 | I42: =H42+(H42*I40) -> 35000000 | J42: =I42+(I42*J40) -> 35000000 | K42: =J42+(J42*K40) -> 35000000 | L42: =K42+(K42*L40) -> 35000000 | M42: =L42+(L42*M40) -> 35000000 | N42: =M42+(M42*N40) -> 35000000 | ... AG42: =AF42+(AF42*AG40) -> 35000000
A44: MONTO CERTIFICADO | F44: =F38*F42 -> 4550000 | G44: =G38*G42 -> 5600000 | H44: =H38*H42 -> 4200000 | I44: =I38*I42 -> 6475000 | J44: =J38*J42 -> 6125000 | K44: =K38*K42 -> 2450000 | L44: =L38*L42 -> 0 | M44: =M38*M42 -> 0 | ... AG44: =AG38*AG42 -> 0
A46: MONTO A PAGAR (con descuento por adelanto) | F46: =F44-(F44*D4) -> 4050800 | G46: =G44-(G44*D4) -> 4985600 | H46: =H44-(H44*D4) -> 3739200 | I46: =I44-(I44*D4) -> 5764600 | J46: =J44-(J44*D4) -> 5453000 | K46: =K44-(K44*D4) -> 2181200 | L46: =L44-(L44*D4) -> 0 | M46: =M44-(M44*D4) -> 0 | N46: =N44-(N44*D4) -> 0 | O46: =O44-(O44*D4) -> 0 | P46: =P44-(P44*D4) -> 0 | Q46: =Q44-(Q44*D4) -> 0 | R46: =R44-(R44*D4) -> 1869600 | S46: =S44-(S44*D4) -> 1869600 | T46: =T44-(T44*D4) -> 1246400 | U46: =U44-(U44*D4) -> 0 | V46: =V44-(V44*D4) -> 0 | W46: =W44-(W44*D4) -> 0 | X46: =X44-(X44*D4) -> 0 | Y46: =Y44-(Y44*D4) -> 0 | Z46: =Z44-(Z44*D4) -> 0 | AA46: =AA44-(AA44*D4) -> 0 | AB46: =AB44-(AB44*D4) -> 0 | AC46: =AC44-(AC44*D4) -> 0 | AD46: =AD44-(AD44*D4) -> 0 | AE46: =AE44-(AE44*D4) -> 0 | AF46: =AF44-(AF44*D4) -> 0 | AG46: =AG44-(AG44*D4) -> 0
A48: SALDO DE OBRA ACTUALIZADO | F48: =F42-F46-C4 -> 27109200 | G48: =(F48+(F48*G40))-G46 -> 22123600 | H48: =(G48+(G48*H40))-H46 -> 18384400 | I48: =(H48+(H48*I40))-I46 -> 12619800 | J48: =(I48+(I48*J40))-J46 -> 7166800 | K48: =(J48+(J48*K40))-K46 -> 4985600 | L48: =(K48+(K48*L40))-L46 -> 4985600 | M48: =(L48+(L48*M40))-M46 -> 4985600 | N48: =(M48+(M48*N40))-N46 -> 4985600 | ... AG48: =(AF48+(AF48*AG40))-AG46 -> 0
A50: PAGO POR MES | F50: =SUM(F46:G46) -> 9036400 | H50: =SUM(H46:I46) -> 9503800 | J50: =SUM(J46:K46) -> 7634200 | L50: =SUM(L46:M46) -> 0 | N50: =SUM(N46:O46) -> 0 | P50: =SUM(P46:Q46) -> 0 | R50: =SUM(R46:S46) -> 3739200 | T50: =SUM(T46:U46) -> 1246400 | V50: =SUM(V46:W46) -> 0 | X50: =SUM(X46:Y46) -> 0 | Z50: =SUM(Z46:AA46) -> 0 | AB50: =SUM(AB46:AC46) -> 0 | AD50: =SUM(AD46:AE46) -> 0 | AF50: =SUM(AF46:AG46) -> 0
G51: =F50*2 -> 18072800 | I51: =H50*2 -> 19007600 | K51: =J50*2 -> 15268400 | M51: =L50*2 -> 0 | O51: =N50*2 -> 0 | Q51: =P50*2 -> 0 | S51: =R50*2 -> 7478400 | U51: =T50*2 -> 2492800 | W51: =V50*2 -> 0 | Y51: =X50*2 -> 0 | AA51: =Z50*2 -> 0 | AC51: =AB50*2 -> 0 | AE51: =AD50*2 -> 0 | AG51: =AF50*2 -> 0

Sheet CASH FLOW sin anticipo
B1: SF - ALBAÑILERÍA BELTRÁN
A2: MES BASE ACTUALIZACIÓN | C2: 46113
A3: MONTO DE OBRA INICIAL | C3: 35000000
A4: ANTICIPO | D4: =C4/C3 -> 0
F5: AGOSTO | H5: SEPTIEMBRE | J5: OCTUBRE | L5: NOVIEMBRE | N5: DICIEMBRE | P5: ENERO | R5: FEBRERO | T5: MARZO | V5: ABRIL | X5: MAYO | Z5: JUNIO | AB5: JULIO | AD5: AGOSTO | AF5: SEPTIEMBRE
A6: ITEM | B6: DESCRIPCIÓN | C6: % ITEM | D6: MONTO TOTAL | E6: FINALIZADO | F6: C1 | H6: C2 | J6: C3 | L6: C4 | N6: C5 | P6: C6 | R6: C7 | T6: C8 | V6: C9 | X6: C10 | Z6: C11 | AB6: C12 | AD6: C13 | AF6: C14
A7: 1 | B7: MAMPOSTERIA | C7: =SUM(C8:C9) -> 0.17 | D7: =C7*C3 -> 5950000 | F7: Q1 | G7: Q2 | H7: Q1 | I7: Q2 | J7: Q1 | K7: Q2 | L7: Q1 | M7: Q2 | N7: Q1 | O7: Q2 | P7: Q1 | Q7: Q2 | R7: Q1 | S7: Q2 | T7: Q1 | U7: Q2 | V7: Q1 | W7: Q2 | X7: Q1 | Y7: Q2 | Z7: Q3 | AA7: Q4 | AB7: Q5 | AC7: Q6 | AD7: Q7 | AE7: Q8 | AF7: Q9 | AG7: Q10
A8: 1 | B8: Módulo completo Brimax | C8: 0.12 | E8: =SUM(F8:AG8) -> 0.12 | F8: 0.1 | G8: 0.02
A9: 2 | B9: Contenciones de acceso a P.B. (Promedio 5m x 0,7h con viga de fundacion) | C9: 0.05 | E9: =SUM(F9:AG9) -> 0.05 | J9: 0.05
A11: 2 | B11: REVOQUES | C11: =SUM(C12) -> 0.15 | D11: =C11*C3 -> 5250000
A12: 1 | B12: Módulo completo | C12: 0.15 | E12: =SUM(F12:AG12) -> 0.15 | I12: 0.075 | J12: 0.075
A14: 3 | B14: AISLACIONES | C14: =SUM(C15:C16) -> 0.12 | D14: =C14*C3 -> 4200000
A15: 1 | B15: Webertec (Exterior + duchas) | C15: 0.06 | E15: =SUM(F15:AG15) -> 0.06 | F15: 0.03 | G15: 0.03
A16: 2 | B16: Exterior (Memb. líquida - incluye cantero dormi) | C16: 0.06 | E16: =SUM(F16:AG16) -> 0.06 | I16: 0.03 | K16: 0.03
A18: 4 | B18: CONTRAPISOS | C18: =SUM(C19:C20) -> 0.18 | D18: =C18*C3 -> 6300000
A19: 1 | B19: Interior duplex | C19: 0.12 | E19: =SUM(F19:AG19) -> 0.12 | G19: 0.03 | H19: 0.09
A20: 2 | B20: Exterior | C20: 0.06 | E20: =SUM(F20:AG20) -> 0.06 | G20: 0.03 | H20: 0.03
A22: 5 | B22: CARPETAS | C22: =SUM(C23:C23) -> 0.06 | D22: =C22*C3 -> 2100000
A23: 1 | B23: Exterior | C23: 0.06 | E23: =SUM(F23:AG23) -> 0.06 | I23: 0.06
A25: 6 | B25: HORMIGÓN | C25: =SUM(C26:C30) -> 0.16 | D25: =C25*C3 -> 5600000
A26: 1 | B26: Banco Tromen | C26: 0.05 | E26: =SUM(F26:AG26) -> 0.05 | J26: 0.05
A27: 2 | B27: Parrilla | C27: 0.05 | E27: =SUM(F27:AG27) -> 0.05 | G27: 0.05
A28: 3 | B28: Banquinas (Parrilla + bauleras) | C28: 0.02 | E28: =SUM(F28:AG28) -> 0.02 | I28: 0.02
A29: 4 | B29: Losetones acceso vehicular | C29: 0.02 | E29: =SUM(F29:AG29) -> 0.02 | K29: 0.02
A30: 5 | B30: Losetones acceso peatonal | C30: 0.02 | E30: =SUM(F30:AG30) -> 0.02 | K30: 0.02
A32: 7 | B32: COLOCACIÓN | C32: =SUM(C33:C36) -> 0.16 | D32: =C32*C3 -> 5600000
A33: 1 | B33: Pisos | C33: 0.06 | E33: =SUM(F33:AG33) -> 0.06 | R33: 0.06
A34: 2 | B34: Baños | C34: 0.06 | E34: =SUM(F34:AG34) -> 0.06 | S34: 0.06
A35: 3 | B35: Cocina | C35: 0.03 | E35: =SUM(F35:AG35) -> 0.03 | T35: 0.03
A36: 4 | B36: Refractarios parrilla | C36: 0.01 | E36: =SUM(F36:AG36) -> 0.01 | T36: 0.01
B38: TOTAL OBRA | C38: =SUM(C7+C11+C14+C18+C22+C25+C32) -> 1 | E38: =SUM(F38:AG38) -> 1 | F38: =SUM(F8:F37) -> 0.13 | G38: =SUM(G8:G37) -> 0.16 | H38: =SUM(H8:H37) -> 0.12 | I38: =SUM(I8:I37) -> 0.185 | J38: =SUM(J8:J37) -> 0.175 | K38: =SUM(K8:K37) -> 0.07 | L38: =SUM(L8:L37) -> 0 | M38: =SUM(M8:M37) -> 0 | ... AG38: =SUM(AG8:AG37) -> 0
A40: AJUSTE | F40: 0 | G40: 0 | H40: 0 | I40: 0 | J40: 0 | K40: 0 | L40: 0 | M40: 0 | N40: 0 | O40: 0 | P40: 0 | Q40: 0 | R40: 0 | S40: 0 | T40: 0 | U40: 0 | V40: 0 | W40: 0 | X40: 0 | Y40: 0 | Z40: 0 | AA40: 0 | AB40: 0 | AC40: 0 | AD40: 0 | AE40: 0 | AF40: 0 | AG40: 0
A42: MONTO DE OBRA ACTUALIZADO | F42: =C3+(C3*F40) -> 35000000 | G42: =F42+(F42*G40) -> 35000000 | H42: =G42+(G42*H40) -> 35000000 | I42: =H42+(H42*I40) -> 35000000 | J42: =I42+(I42*J40) -> 35000000 | K42: =J42+(J42*K40) -> 35000000 | L42: =K42+(K42*L40) -> 35000000 | M42: =L42+(L42*M40) -> 35000000 | N42: =M42+(M42*N40) -> 35000000 | ... AG42: =AF42+(AF42*AG40) -> 35000000
A44: MONTO CERTIFICADO | F44: =F38*F42 -> 4550000 | G44: =G38*G42 -> 5600000 | H44: =H38*H42 -> 4200000 | I44: =I38*I42 -> 6475000 | J44: =J38*J42 -> 6125000 | K44: =K38*K42 -> 2450000 | L44: =L38*L42 -> 0 | M44: =M38*M42 -> 0 | ... AG44: =AG38*AG42 -> 0
A46: MONTO A PAGAR (con descuento por adelanto) | F46: =F44-(F44*D4) -> 4550000 | G46: =G44-(G44*D4) -> 5600000 | H46: =H44-(H44*D4) -> 4200000 | I46: =I44-(I44*D4) -> 6475000 | J46: =J44-(J44*D4) -> 6125000 | K46: =K44-(K44*D4) -> 2450000 | L46: =L44-(L44*D4) -> 0 | M46: =M44-(M44*D4) -> 0 | N46: =N44-(N44*D4) -> 0 | O46: =O44-(O44*D4) -> 0 | P46: =P44-(P44*D4) -> 0 | Q46: =Q44-(Q44*D4) -> 0 | R46: =R44-(R44*D4) -> 2100000 | S46: =S44-(S44*D4) -> 2100000 | T46: =T44-(T44*D4) -> 1400000 | U46: =U44-(U44*D4) -> 0 | V46: =V44-(V44*D4) -> 0 | W46: =W44-(W44*D4) -> 0 | X46: =X44-(X44*D4) -> 0 | Y46: =Y44-(Y44*D4) -> 0 | Z46: =Z44-(Z44*D4) -> 0 | AA46: =AA44-(AA44*D4) -> 0 | AB46: =AB44-(AB44*D4) -> 0 | AC46: =AC44-(AC44*D4) -> 0 | AD46: =AD44-(AD44*D4) -> 0 | AE46: =AE44-(AE44*D4) -> 0 | AF46: =AF44-(AF44*D4) -> 0 | AG46: =AG44-(AG44*D4) -> 0
A48: SALDO DE OBRA ACTUALIZADO | F48: =F42-F46-C4 -> 30450000 | G48: =(F48+(F48*G40))-G46 -> 24850000 | H48: =(G48+(G48*H40))-H46 -> 20650000 | I48: =(H48+(H48*I40))-I46 -> 14175000 | J48: =(I48+(I48*J40))-J46 -> 8050000 | K48: =(J48+(J48*K40))-K46 -> 5600000 | L48: =(K48+(K48*L40))-L46 -> 5600000 | M48: =(L48+(L48*M40))-M46 -> 5600000 | N48: =(M48+(M48*N40))-N46 -> 5600000 | ... AG48: =(AF48+(AF48*AG40))-AG46 -> 0
A50: PAGO POR MES | F50: =SUM(F46:G46) -> 10150000 | H50: =SUM(H46:I46) -> 10675000 | J50: =SUM(J46:K46) -> 8575000 | L50: =SUM(L46:M46) -> 0 | N50: =SUM(N46:O46) -> 0 | P50: =SUM(P46:Q46) -> 0 | R50: =SUM(R46:S46) -> 4200000 | T50: =SUM(T46:U46) -> 1400000 | V50: =SUM(V46:W46) -> 0 | X50: =SUM(X46:Y46) -> 0 | Z50: =SUM(Z46:AA46) -> 0 | AB50: =SUM(AB46:AC46) -> 0 | AD50: =SUM(AD46:AE46) -> 0 | AF50: =SUM(AF46:AG46) -> 0

Sheet M11
B1: SF - ALBAÑILERÍA BELTRÁN
A2: MES BASE ACTUALIZACIÓN | C2: 46113
A3: MONTO DE OBRA INICIAL | C3: 35000000
A4: ANTICIPO | C4: 3840000 | D4: =C4/C3 -> 0.10971429
F5: MAYO | H5: JUNIO | J5: JULIO | L5: AGOSTO | N5: SEPTIEMBRE | P5: OCTUBRE | R5: NOVIEMBRE | T5: DICIEMBRE | V5: ENERO | X5: FEBRERO | Z5: MARZO | AB5: ABRIL | AD5: MAYO | AF5: JUNIO
A6: ITEM | B6: DESCRIPCIÓN | C6: % ITEM | D6: MONTO TOTAL | E6: FINALIZADO | F6: C1 | H6: C2 | J6: C3 | L6: C4 | N6: C5 | P6: C6 | R6: C7 | T6: C8 | V6: C9 | X6: C10 | Z6: C11 | AB6: C12 | AD6: C13 | AF6: C14
A7: 1 | B7: MAMPOSTERIA | C7: =SUM(C8:C9) -> 0.17 | D7: =C7*C3 -> 5950000 | F7: Q1 | G7: Q2 | H7: Q1 | I7: Q2 | J7: Q1 | K7: Q2 | L7: Q1 | M7: Q2 | N7: Q1 | O7: Q2 | P7: Q1 | Q7: Q2 | R7: Q1 | S7: Q2 | T7: Q1 | U7: Q2 | V7: Q1 | W7: Q2 | X7: Q1 | Y7: Q2 | Z7: Q3 | AA7: Q4 | AB7: Q5 | AC7: Q6 | AD7: Q7 | AE7: Q8 | AF7: Q9 | AG7: Q10
A8: 1 | B8: Módulo completo Brimax | C8: 0.12 | E8: =SUM(F8:AG8) -> 0.12 | F8: 0.1 | G8: 0.02
A9: 2 | B9: Contenciones de acceso a P.B. (Promedio 5m x 0,7h con viga de fundacion) | C9: 0.05 | E9: =SUM(F9:AG9) -> 0
A11: 2 | B11: REVOQUES | C11: =SUM(C12) -> 0.15 | D11: =C11*C3 -> 5250000
A12: 1 | B12: Módulo completo | C12: 0.15 | E12: =SUM(F12:AG12) -> 0.02 | I12: 0.02
A14: 3 | B14: AISLACIONES | C14: =SUM(C15:C16) -> 0.12 | D14: =C14*C3 -> 4200000
A15: 1 | B15: Webertec (Exterior + duchas) | C15: 0.06 | E15: =SUM(F15:AG15) -> 0.06 | G15: 0.04 | I15: 0.02
A16: 2 | B16: Exterior (Memb. líquida - incluye cantero dormi) | C16: 0.06 | E16: =SUM(F16:AG16) -> 0.03 | F16: 0.03
A18: 4 | B18: CONTRAPISOS | C18: =SUM(C19:C20) -> 0.18 | D18: =C18*C3 -> 6300000
A19: 1 | B19: Interior duplex | C19: 0.12 | E19: =SUM(F19:AG19) -> 0.12 | G19: 0.04 | H19: 0.06 | I19: 0.02
A20: 2 | B20: Exterior | C20: 0.06 | E20: =SUM(F20:AG20) -> 0.06 | G20: 0.02 | H20: 0.02 | I20: 0.02
A22: 5 | B22: CARPETAS | C22: =SUM(C23:C23) -> 0.06 | D22: =C22*C3 -> 2100000
A23: 1 | B23: Exterior | C23: 0.06 | E23: =SUM(F23:AG23) -> 0.06 | I23: 0.06
A25: 6 | B25: HORMIGÓN | C25: =SUM(C26:C30) -> 0.16 | D25: =C25*C3 -> 5600000
A26: 1 | B26: Banco Tromen | C26: 0.05 | E26: =SUM(F26:AG26) -> 0.01 | I26: 0.01
A27: 2 | B27: Parrilla | C27: 0.05 | E27: =SUM(F27:AG27) -> 0.03 | G27: 0.03
A28: 3 | B28: Banquinas (Parrilla + bauleras) | C28: 0.02 | E28: =SUM(F28:AG28) -> 0
A29: 4 | B29: Losetones acceso vehicular | C29: 0.02 | E29: =SUM(F29:AG29) -> 0
A30: 5 | B30: Losetones acceso peatonal | C30: 0.02 | E30: =SUM(F30:AG30) -> 0
A32: 7 | B32: COLOCACIÓN | C32: =SUM(C33:C36) -> 0.16 | D32: =C32*C3 -> 5600000
A33: 1 | B33: Pisos | C33: 0.06 | E33: =SUM(F33:AG33) -> 0
A34: 2 | B34: Baños | C34: 0.06 | E34: =SUM(F34:AG34) -> 0
A35: 3 | B35: Cocina | C35: 0.03 | E35: =SUM(F35:AG35) -> 0
A36: 4 | B36: Refractarios parrilla | C36: 0.01 | E36: =SUM(F36:AG36) -> 0
B38: TOTAL OBRA | C38: =SUM(C7+C11+C14+C18+C22+C25+C32) -> 1 | E38: =SUM(F38:AG38) -> 0.51 | F38: =SUM(F8:F37) -> 0.13 | G38: =SUM(G8:G37) -> 0.15 | H38: =SUM(H8:H37) -> 0.08 | I38: =SUM(I8:I37) -> 0.15 | J38: =SUM(J8:J37) -> 0 | K38: =SUM(K8:K37) -> 0 | L38: =SUM(L8:L37) -> 0 | M38: =SUM(M8:M37) -> 0 | ... AG38: =SUM(AG8:AG37) -> 0
A40: AJUSTE | F40: 0 | G40: 0 | H40: 0 | I40: 0 | J40: 0 | K40: 0 | L40: 0 | M40: 0 | N40: 0 | O40: 0 | P40: 0 | Q40: 0 | R40: 0 | S40: 0 | T40: 0 | U40: 0 | V40: 0 | W40: 0 | X40: 0 | Y40: 0 | Z40: 0 | AA40: 0 | AB40: 0 | AC40: 0 | AD40: 0 | AE40: 0 | AF40: 0 | AG40: 0
A42: MONTO DE OBRA ACTUALIZADO | F42: =C3+(C3*F40) -> 35000000 | G42: =F42+(F42*G40) -> 35000000 | H42: =G42+(G42*H40) -> 35000000 | I42: =H42+(H42*I40) -> 35000000 | J42: =I42+(I42*J40) -> 35000000 | K42: =J42+(J42*K40) -> 35000000 | L42: =K42+(K42*L40) -> 35000000 | M42: =L42+(L42*M40) -> 35000000 | N42: =M42+(M42*N40) -> 35000000 | ... AG42: =AF42+(AF42*AG40) -> 35000000
A44: MONTO CERTIFICADO | F44: =F38*F42 -> 4550000 | G44: =G38*G42 -> 5250000 | H44: =H38*H42 -> 2800000 | I44: =I38*I42 -> 5250000 | J44: =J38*J42 -> 0 | K44: =K38*K42 -> 0 | L44: =L38*L42 -> 0 | M44: =M38*M42 -> 0 | ... AG44: =AG38*AG42 -> 0
A46: MONTO A PAGAR (con descuento por adelanto) | F46: =F44-(F44*D4) -> 4050800 | G46: =G44-(G44*D4) -> 4674000 | H46: =H44-(H44*D4) -> 2492800 | I46: =I44-(I44*D4) -> 4674000 | J46: =J44-(J44*D4) -> 0 | K46: =K44-(K44*D4) -> 0 | L46: =L44-(L44*D4) -> 0 | M46: =M44-(M44*D4) -> 0 | N46: =N44-(N44*D4) -> 0 | O46: =O44-(O44*D4) -> 0 | P46: =P44-(P44*D4) -> 0 | Q46: =Q44-(Q44*D4) -> 0 | R46: =R44-(R44*D4) -> 0 | S46: =S44-(S44*D4) -> 0 | T46: =T44-(T44*D4) -> 0 | U46: =U44-(U44*D4) -> 0 | V46: =V44-(V44*D4) -> 0 | W46: =W44-(W44*D4) -> 0 | X46: =X44-(X44*D4) -> 0 | Y46: =Y44-(Y44*D4) -> 0 | Z46: =Z44-(Z44*D4) -> 0 | AA46: =AA44-(AA44*D4) -> 0 | AB46: =AB44-(AB44*D4) -> 0 | AC46: =AC44-(AC44*D4) -> 0 | AD46: =AD44-(AD44*D4) -> 0 | AE46: =AE44-(AE44*D4) -> 0 | AF46: =AF44-(AF44*D4) -> 0 | AG46: =AG44-(AG44*D4) -> 0
A48: SALDO DE OBRA ACTUALIZADO | F48: =F42-F46-C4 -> 27109200 | G48: =(F48+(F48*G40))-G46 -> 22435200 | H48: =(G48+(G48*H40))-H46 -> 19942400 | I48: =(H48+(H48*I40))-I46 -> 15268400 | J48: =(I48+(I48*J40))-J46 -> 15268400 | K48: =(J48+(J48*K40))-K46 -> 15268400 | L48: =(K48+(K48*L40))-L46 -> 15268400 | M48: =(L48+(L48*M40))-M46 -> 15268400 | N48: =(M48+(M48*N40))-N46 -> 15268400 | ... AG48: =(AF48+(AF48*AG40))-AG46 -> 15268400

Sheet M10
B1: SF - ALBAÑILERÍA BELTRÁN
A2: MES BASE ACTUALIZACIÓN | C2: 46113
A3: MONTO DE OBRA INICIAL | C3: 35000000
A4: ANTICIPO | C4: 3840000 | D4: =C4/C3 -> 0.10971429
F5: MAYO | H5: JUNIO | J5: JULIO | L5: AGOSTO | N5: SEPTIEMBRE | P5: OCTUBRE | R5: NOVIEMBRE | T5: DICIEMBRE | V5: ENERO | X5: FEBRERO | Z5: MARZO | AB5: ABRIL | AD5: MAYO | AF5: JUNIO
A6: ITEM | B6: DESCRIPCIÓN | C6: % ITEM | D6: MONTO TOTAL | E6: FINALIZADO | F6: C1 | H6: C2 | J6: C3 | L6: C4 | N6: C5 | P6: C6 | R6: C7 | T6: C8 | V6: C9 | X6: C10 | Z6: C11 | AB6: C12 | AD6: C13 | AF6: C14
A7: 1 | B7: MAMPOSTERIA | C7: =SUM(C8:C9) -> 0.17 | D7: =C7*C3 -> 5950000 | F7: Q1 | G7: Q2 | H7: Q1 | I7: Q2 | J7: Q1 | K7: Q2 | L7: Q1 | M7: Q2 | N7: Q1 | O7: Q2 | P7: Q1 | Q7: Q2 | R7: Q1 | S7: Q2 | T7: Q1 | U7: Q2 | V7: Q1 | W7: Q2 | X7: Q1 | Y7: Q2 | Z7: Q3 | AA7: Q4 | AB7: Q5 | AC7: Q6 | AD7: Q7 | AE7: Q8 | AF7: Q9 | AG7: Q10
A8: 1 | B8: Módulo completo Brimax | C8: 0.12 | E8: =SUM(F8:AG8) -> 0.12 | F8: 0.1 | G8: 0.02
A9: 2 | B9: Contenciones de acceso a P.B. (Promedio 5m x 0,7h con viga de fundacion) | C9: 0.05 | E9: =SUM(F9:AG9) -> 0
A11: 2 | B11: REVOQUES | C11: =SUM(C12) -> 0.15 | D11: =C11*C3 -> 5250000
A12: 1 | B12: Módulo completo | C12: 0.15 | E12: =SUM(F12:AG12) -> 0.02 | I12: 0.02
A14: 3 | B14: AISLACIONES | C14: =SUM(C15:C16) -> 0.12 | D14: =C14*C3 -> 4200000
A15: 1 | B15: Webertec (Exterior + duchas) | C15: 0.06 | E15: =SUM(F15:AG15) -> 0.06 | G15: 0.04 | I15: 0.02
A16: 2 | B16: Exterior (Memb. líquida - incluye cantero dormi) | C16: 0.06 | E16: =SUM(F16:AG16) -> 0.03 | F16: 0.03
A18: 4 | B18: CONTRAPISOS | C18: =SUM(C19:C20) -> 0.18 | D18: =C18*C3 -> 6300000
A19: 1 | B19: Interior duplex | C19: 0.12 | E19: =SUM(F19:AG19) -> 0.12 | G19: 0.04 | H19: 0.06 | I19: 0.02
A20: 2 | B20: Exterior | C20: 0.06 | E20: =SUM(F20:AG20) -> 0.06 | G20: 0.02 | H20: 0.02 | I20: 0.02
A22: 5 | B22: CARPETAS | C22: =SUM(C23:C23) -> 0.06 | D22: =C22*C3 -> 2100000
A23: 1 | B23: Exterior | C23: 0.06 | E23: =SUM(F23:AG23) -> 0.06 | I23: 0.06
A25: 6 | B25: HORMIGÓN | C25: =SUM(C26:C30) -> 0.16 | D25: =C25*C3 -> 5600000
A26: 1 | B26: Banco Tromen | C26: 0.05 | E26: =SUM(F26:AG26) -> 0.01 | I26: 0.01
A27: 2 | B27: Parrilla | C27: 0.05 | E27: =SUM(F27:AG27) -> 0.03 | G27: 0.03
A28: 3 | B28: Banquinas (Parrilla + bauleras) | C28: 0.02 | E28: =SUM(F28:AG28) -> 0
A29: 4 | B29: Losetones acceso vehicular | C29: 0.02 | E29: =SUM(F29:AG29) -> 0
A30: 5 | B30: Losetones acceso peatonal | C30: 0.02 | E30: =SUM(F30:AG30) -> 0
A32: 7 | B32: COLOCACIÓN | C32: =SUM(C33:C36) -> 0.16 | D32: =C32*C3 -> 5600000
A33: 1 | B33: Pisos | C33: 0.06 | E33: =SUM(F33:AG33) -> 0
A34: 2 | B34: Baños | C34: 0.06 | E34: =SUM(F34:AG34) -> 0
A35: 3 | B35: Cocina | C35: 0.03 | E35: =SUM(F35:AG35) -> 0
A36: 4 | B36: Refractarios parrilla | C36: 0.01 | E36: =SUM(F36:AG36) -> 0
B38: TOTAL OBRA | C38: =SUM(C7+C11+C14+C18+C22+C25+C32) -> 1 | E38: =SUM(F38:AG38) -> 0.51 | F38: =SUM(F8:F37) -> 0.13 | G38: =SUM(G8:G37) -> 0.15 | H38: =SUM(H8:H37) -> 0.08 | I38: =SUM(I8:I37) -> 0.15 | J38: =SUM(J8:J37) -> 0 | K38: =SUM(K8:K37) -> 0 | L38: =SUM(L8:L37) -> 0 | M38: =SUM(M8:M37) -> 0 | ... AG38: =SUM(AG8:AG37) -> 0
A40: AJUSTE | F40: 0 | G40: 0 | H40: 0 | I40: 0 | J40: 0 | K40: 0 | L40: 0 | M40: 0 | N40: 0 | O40: 0 | P40: 0 | Q40: 0 | R40: 0 | S40: 0 | T40: 0 | U40: 0 | V40: 0 | W40: 0 | X40: 0 | Y40: 0 | Z40: 0 | AA40: 0 | AB40: 0 | AC40: 0 | AD40: 0 | AE40: 0 | AF40: 0 | AG40: 0
A42: MONTO DE OBRA ACTUALIZADO | F42: =C3+(C3*F40) -> 35000000 | G42: =F42+(F42*G40) -> 35000000 | H42: =G42+(G42*H40) -> 35000000 | I42: =H42+(H42*I40) -> 35000000 | J42: =I42+(I42*J40) -> 35000000 | K42: =J42+(J42*K40) -> 35000000 | L42: =K42+(K42*L40) -> 35000000 | M42: =L42+(L42*M40) -> 35000000 | N42: =M42+(M42*N40) -> 35000000 | ... AG42: =AF42+(AF42*AG40) -> 35000000
A44: MONTO CERTIFICADO | F44: =F38*F42 -> 4550000 | G44: =G38*G42 -> 5250000 | H44: =H38*H42 -> 2800000 | I44: =I38*I42 -> 5250000 | J44: =J38*J42 -> 0 | K44: =K38*K42 -> 0 | L44: =L38*L42 -> 0 | M44: =M38*M42 -> 0 | ... AG44: =AG38*AG42 -> 0
A46: MONTO A PAGAR (con descuento por adelanto) | F46: =F44-(F44*D4) -> 4050800 | G46: =G44-(G44*D4) -> 4674000 | H46: =H44-(H44*D4) -> 2492800 | I46: =I44-(I44*D4) -> 4674000 | J46: =J44-(J44*D4) -> 0 | K46: =K44-(K44*D4) -> 0 | L46: =L44-(L44*D4) -> 0 | M46: =M44-(M44*D4) -> 0 | N46: =N44-(N44*D4) -> 0 | O46: =O44-(O44*D4) -> 0 | P46: =P44-(P44*D4) -> 0 | Q46: =Q44-(Q44*D4) -> 0 | R46: =R44-(R44*D4) -> 0 | S46: =S44-(S44*D4) -> 0 | T46: =T44-(T44*D4) -> 0 | U46: =U44-(U44*D4) -> 0 | V46: =V44-(V44*D4) -> 0 | W46: =W44-(W44*D4) -> 0 | X46: =X44-(X44*D4) -> 0 | Y46: =Y44-(Y44*D4) -> 0 | Z46: =Z44-(Z44*D4) -> 0 | AA46: =AA44-(AA44*D4) -> 0 | AB46: =AB44-(AB44*D4) -> 0 | AC46: =AC44-(AC44*D4) -> 0 | AD46: =AD44-(AD44*D4) -> 0 | AE46: =AE44-(AE44*D4) -> 0 | AF46: =AF44-(AF44*D4) -> 0 | AG46: =AG44-(AG44*D4) -> 0
A48: SALDO DE OBRA ACTUALIZADO | F48: =F42-F46-C4 -> 27109200 | G48: =(F48+(F48*G40))-G46 -> 22435200 | H48: =(G48+(G48*H40))-H46 -> 19942400 | I48: =(H48+(H48*I40))-I46 -> 15268400 | J48: =(I48+(I48*J40))-J46 -> 15268400 | K48: =(J48+(J48*K40))-K46 -> 15268400 | L48: =(K48+(K48*L40))-L46 -> 15268400 | M48: =(L48+(L48*M40))-M46 -> 15268400 | N48: =(M48+(M48*N40))-N46 -> 15268400 | ... AG48: =(AF48+(AF48*AG40))-AG46 -> 15268400

Sheet M08
B1: SF - ALBAÑILERÍA BELTRÁN
A2: MES BASE ACTUALIZACIÓN | C2: 46113
A3: MONTO DE OBRA INICIAL | C3: 35000000
A4: ANTICIPO | C4: 0 | D4: =C4/C3 -> 0
F5: JUNIO | H5: JULIO | J5: AGOSTO | L5: SEPTIEMBRE | N5: OCTUBRE | P5: NOVIEMBRE | R5: DICIEMBRE | T5: ENERO | V5: FEBRERO | X5: MARZO | Z5: ABRIL | AB5: MAYO | AD5: JUNIO | AF5: JULIO
A6: ITEM | B6: DESCRIPCIÓN | C6: % ITEM | D6: MONTO TOTAL | E6: FINALIZADO | F6: C1 | H6: C2 | J6: C3 | L6: C4 | N6: C5 | P6: C6 | R6: C7 | T6: C8 | V6: C9 | X6: C10 | Z6: C11 | AB6: C12 | AD6: C13 | AF6: C14
A7: 1 | B7: MAMPOSTERIA | C7: =SUM(C8:C9) -> 0.17 | D7: =C7*C3 -> 5950000 | F7: Q1 | G7: Q2 | H7: Q1 | I7: Q2 | J7: Q1 | K7: Q2 | L7: Q1 | M7: Q2 | N7: Q1 | O7: Q2 | P7: Q1 | Q7: Q2 | R7: Q1 | S7: Q2 | T7: Q1 | U7: Q2 | V7: Q1 | W7: Q2 | X7: Q1 | Y7: Q2 | Z7: Q3 | AA7: Q4 | AB7: Q5 | AC7: Q6 | AD7: Q7 | AE7: Q8 | AF7: Q9 | AG7: Q10
A8: 1 | B8: Módulo completo Brimax | C8: 0.12 | E8: =SUM(F8:AG8) -> 0.07 | F8: 0.07
A9: 2 | B9: Contenciones de acceso a P.B. (Promedio 5m x 0,7h con viga de fundacion) | C9: 0.05 | E9: =SUM(F9:AG9) -> 0
A11: 2 | B11: REVOQUES | C11: =SUM(C12) -> 0.15 | D11: =C11*C3 -> 5250000
A12: 1 | B12: Módulo completo | C12: 0.15 | E12: =SUM(F12:AG12) -> 0
A14: 3 | B14: AISLACIONES | C14: =SUM(C15:C16) -> 0.12 | D14: =C14*C3 -> 4200000
A15: 1 | B15: Webertec (Exterior + duchas) | C15: 0.06 | E15: =SUM(F15:AG15) -> 0
A16: 2 | B16: Exterior (Memb. líquida - incluye cantero dormi) | C16: 0.06 | E16: =SUM(F16:AG16) -> 0
A18: 4 | B18: CONTRAPISOS | C18: =SUM(C19:C20) -> 0.18 | D18: =C18*C3 -> 6300000
A19: 1 | B19: Interior duplex | C19: 0.12 | E19: =SUM(F19:AG19) -> 0
A20: 2 | B20: Exterior | C20: 0.06 | E20: =SUM(F20:AG20) -> 0
A22: 5 | B22: CARPETAS | C22: =SUM(C23:C23) -> 0.06 | D22: =C22*C3 -> 2100000
A23: 1 | B23: Exterior | C23: 0.06 | E23: =SUM(F23:AG23) -> 0
A25: 6 | B25: HORMIGÓN | C25: =SUM(C26:C30) -> 0.16 | D25: =C25*C3 -> 5600000
A26: 1 | B26: Banco Tromen | C26: 0.05 | E26: =SUM(F26:AG26) -> 0
A27: 2 | B27: Parrilla | C27: 0.05 | E27: =SUM(F27:AG27) -> 0
A28: 3 | B28: Banquinas (Parrilla + bauleras) | C28: 0.02 | E28: =SUM(F28:AG28) -> 0
A29: 4 | B29: Losetones acceso vehicular | C29: 0.02 | E29: =SUM(F29:AG29) -> 0
A30: 5 | B30: Losetones acceso peatonal | C30: 0.02 | E30: =SUM(F30:AG30) -> 0
A32: 7 | B32: COLOCACIÓN | C32: =SUM(C33:C36) -> 0.16 | D32: =C32*C3 -> 5600000
A33: 1 | B33: Pisos | C33: 0.06 | E33: =SUM(F33:AG33) -> 0
A34: 2 | B34: Baños | C34: 0.06 | E34: =SUM(F34:AG34) -> 0
A35: 3 | B35: Cocina | C35: 0.03 | E35: =SUM(F35:AG35) -> 0
A36: 4 | B36: Refractarios parrilla | C36: 0.01 | E36: =SUM(F36:AG36) -> 0
B38: TOTAL OBRA | C38: =SUM(C7+C11+C14+C18+C22+C25+C32) -> 1 | E38: =SUM(F38:AG38) -> 0.07 | F38: =SUM(F8:F37) -> 0.07 | G38: =SUM(G8:G37) -> 0 | H38: =SUM(H8:H37) -> 0 | I38: =SUM(I8:I37) -> 0 | J38: =SUM(J8:J37) -> 0 | K38: =SUM(K8:K37) -> 0 | L38: =SUM(L8:L37) -> 0 | M38: =SUM(M8:M37) -> 0 | ... AG38: =SUM(AG8:AG37) -> 0
A40: AJUSTE | F40: 0 | G40: 0 | H40: 0 | I40: 0 | J40: 0 | K40: 0 | L40: 0 | M40: 0 | N40: 0 | O40: 0 | P40: 0 | Q40: 0 | R40: 0 | S40: 0 | T40: 0 | U40: 0 | V40: 0 | W40: 0 | X40: 0 | Y40: 0 | Z40: 0 | AA40: 0 | AB40: 0 | AC40: 0 | AD40: 0 | AE40: 0 | AF40: 0 | AG40: 0
A42: MONTO DE OBRA ACTUALIZADO | F42: =C3+(C3*F40) -> 35000000 | G42: =F42+(F42*G40) -> 35000000 | H42: =G42+(G42*H40) -> 35000000 | I42: =H42+(H42*I40) -> 35000000 | J42: =I42+(I42*J40) -> 35000000 | K42: =J42+(J42*K40) -> 35000000 | L42: =K42+(K42*L40) -> 35000000 | M42: =L42+(L42*M40) -> 35000000 | N42: =M42+(M42*N40) -> 35000000 | ... AG42: =AF42+(AF42*AG40) -> 35000000
A44: MONTO CERTIFICADO | F44: =F38*F42 -> 2450000 | G44: =G38*G42 -> 0 | H44: =H38*H42 -> 0 | I44: =I38*I42 -> 0 | J44: =J38*J42 -> 0 | K44: =K38*K42 -> 0 | L44: =L38*L42 -> 0 | M44: =M38*M42 -> 0 | ... AG44: =AG38*AG42 -> 0
A46: MONTO A PAGAR (con descuento por adelanto) | F46: =F44-(F44*D4) -> 2450000 | G46: =G44-(G44*D4) -> 0 | H46: =H44-(H44*D4) -> 0 | I46: =I44-(I44*D4) -> 0 | J46: =J44-(J44*D4) -> 0 | K46: =K44-(K44*D4) -> 0 | L46: =L44-(L44*D4) -> 0 | M46: =M44-(M44*D4) -> 0 | N46: =N44-(N44*D4) -> 0 | O46: =O44-(O44*D4) -> 0 | P46: =P44-(P44*D4) -> 0 | Q46: =Q44-(Q44*D4) -> 0 | R46: =R44-(R44*D4) -> 0 | S46: =S44-(S44*D4) -> 0 | T46: =T44-(T44*D4) -> 0 | U46: =U44-(U44*D4) -> 0 | V46: =V44-(V44*D4) -> 0 | W46: =W44-(W44*D4) -> 0 | X46: =X44-(X44*D4) -> 0 | Y46: =Y44-(Y44*D4) -> 0 | Z46: =Z44-(Z44*D4) -> 0 | AA46: =AA44-(AA44*D4) -> 0 | AB46: =AB44-(AB44*D4) -> 0 | AC46: =AC44-(AC44*D4) -> 0 | AD46: =AD44-(AD44*D4) -> 0 | AE46: =AE44-(AE44*D4) -> 0 | AF46: =AF44-(AF44*D4) -> 0 | AG46: =AG44-(AG44*D4) -> 0
A48: SALDO DE OBRA ACTUALIZADO | F48: =F42-F46-C4 -> 32550000 | G48: =(F48+(F48*G40))-G46 -> 32550000 | H48: =(G48+(G48*H40))-H46 -> 32550000 | I48: =(H48+(H48*I40))-I46 -> 32550000 | J48: =(I48+(I48*J40))-J46 -> 32550000 | K48: =(J48+(J48*K40))-K46 -> 32550000 | L48: =(K48+(K48*L40))-L46 -> 32550000 | M48: =(L48+(L48*M40))-M46 -> 32550000 | N48: =(M48+(M48*N40))-N46 -> 32550000 | ... AG48: =(AF48+(AF48*AG40))-AG46 -> 32550000

Sheet M07
B1: SF - ALBAÑILERÍA BELTRÁN
A2: MES BASE ACTUALIZACIÓN | C2: 46113
A3: MONTO DE OBRA INICIAL | C3: 35000000
A4: ANTICIPO | C4: 0 | D4: =C4/C3 -> 0
F5: AGOSTO | H5: SEPTIEMBRE | J5: OCTUBRE | L5: NOVIEMBRE | N5: DICIEMBRE | P5: ENERO | R5: FEBRERO | T5: MARZO | V5: ABRIL | X5: MAYO | Z5: JUNIO | AB5: JULIO | AD5: AGOSTO | AF5: SEPTIEMBRE
A6: ITEM | B6: DESCRIPCIÓN | C6: % ITEM | D6: MONTO TOTAL | E6: FINALIZADO | F6: C1 | H6: C2 | J6: C3 | L6: C4 | N6: C5 | P6: C6 | R6: C7 | T6: C8 | V6: C9 | X6: C10 | Z6: C11 | AB6: C12 | AD6: C13 | AF6: C14
A7: 1 | B7: MAMPOSTERIA | C7: =SUM(C8:C9) -> 0.17 | D7: =C7*C3 -> 5950000 | F7: Q1 | G7: Q2 | H7: Q1 | I7: Q2 | J7: Q1 | K7: Q2 | L7: Q1 | M7: Q2 | N7: Q1 | O7: Q2 | P7: Q1 | Q7: Q2 | R7: Q1 | S7: Q2 | T7: Q1 | U7: Q2 | V7: Q1 | W7: Q2 | X7: Q1 | Y7: Q2 | Z7: Q3 | AA7: Q4 | AB7: Q5 | AC7: Q6 | AD7: Q7 | AE7: Q8 | AF7: Q9 | AG7: Q10
A8: 1 | B8: Módulo completo Brimax | C8: 0.12 | E8: =SUM(F8:AG8) -> 0
A9: 2 | B9: Contenciones de acceso a P.B. (Promedio 5m x 0,7h con viga de fundacion) | C9: 0.05 | E9: =SUM(F9:AG9) -> 0
A11: 2 | B11: REVOQUES | C11: =SUM(C12) -> 0.15 | D11: =C11*C3 -> 5250000
A12: 1 | B12: Módulo completo | C12: 0.15 | E12: =SUM(F12:AG12) -> 0
A14: 3 | B14: AISLACIONES | C14: =SUM(C15:C16) -> 0.12 | D14: =C14*C3 -> 4200000
A15: 1 | B15: Webertec (Exterior + duchas) | C15: 0.06 | E15: =SUM(F15:AG15) -> 0
A16: 2 | B16: Exterior (Memb. líquida - incluye cantero dormi) | C16: 0.06 | E16: =SUM(F16:AG16) -> 0
A18: 4 | B18: CONTRAPISOS | C18: =SUM(C19:C20) -> 0.18 | D18: =C18*C3 -> 6300000
A19: 1 | B19: Interior duplex | C19: 0.12 | E19: =SUM(F19:AG19) -> 0
A20: 2 | B20: Exterior | C20: 0.06 | E20: =SUM(F20:AG20) -> 0
A22: 5 | B22: CARPETAS | C22: =SUM(C23:C23) -> 0.06 | D22: =C22*C3 -> 2100000
A23: 1 | B23: Exterior | C23: 0.06 | E23: =SUM(F23:AG23) -> 0
A25: 6 | B25: HORMIGÓN | C25: =SUM(C26:C30) -> 0.16 | D25: =C25*C3 -> 5600000
A26: 1 | B26: Banco Tromen | C26: 0.05 | E26: =SUM(F26:AG26) -> 0
A27: 2 | B27: Parrilla | C27: 0.05 | E27: =SUM(F27:AG27) -> 0
A28: 3 | B28: Banquinas (Parrilla + bauleras) | C28: 0.02 | E28: =SUM(F28:AG28) -> 0
A29: 4 | B29: Losetones acceso vehicular | C29: 0.02 | E29: =SUM(F29:AG29) -> 0
A30: 5 | B30: Losetones acceso peatonal | C30: 0.02 | E30: =SUM(F30:AG30) -> 0
A32: 7 | B32: COLOCACIÓN | C32: =SUM(C33:C36) -> 0.16 | D32: =C32*C3 -> 5600000
A33: 1 | B33: Pisos | C33: 0.06 | E33: =SUM(F33:AG33) -> 0
A34: 2 | B34: Baños | C34: 0.06 | E34: =SUM(F34:AG34) -> 0
A35: 3 | B35: Cocina | C35: 0.03 | E35: =SUM(F35:AG35) -> 0
A36: 4 | B36: Refractarios parrilla | C36: 0.01 | E36: =SUM(F36:AG36) -> 0
B38: TOTAL OBRA | C38: =SUM(C7+C11+C14+C18+C22+C25+C32) -> 1 | E38: =SUM(F38:AG38) -> 0 | F38: =SUM(F8:F37) -> 0 | G38: =SUM(G8:G37) -> 0 | H38: =SUM(H8:H37) -> 0 | I38: =SUM(I8:I37) -> 0 | J38: =SUM(J8:J37) -> 0 | K38: =SUM(K8:K37) -> 0 | L38: =SUM(L8:L37) -> 0 | M38: =SUM(M8:M37) -> 0 | ... AG38: =SUM(AG8:AG37) -> 0
A40: AJUSTE | F40: 0 | G40: 0 | H40: 0 | I40: 0 | J40: 0 | K40: 0 | L40: 0 | M40: 0 | N40: 0 | O40: 0 | P40: 0 | Q40: 0 | R40: 0 | S40: 0 | T40: 0 | U40: 0 | V40: 0 | W40: 0 | X40: 0 | Y40: 0 | Z40: 0 | AA40: 0 | AB40: 0 | AC40: 0 | AD40: 0 | AE40: 0 | AF40: 0 | AG40: 0
A42: MONTO DE OBRA ACTUALIZADO | F42: =C3+(C3*F40) -> 35000000 | G42: =F42+(F42*G40) -> 35000000 | H42: =G42+(G42*H40) -> 35000000 | I42: =H42+(H42*I40) -> 35000000 | J42: =I42+(I42*J40) -> 35000000 | K42: =J42+(J42*K40) -> 35000000 | L42: =K42+(K42*L40) -> 35000000 | M42: =L42+(L42*M40) -> 35000000 | N42: =M42+(M42*N40) -> 35000000 | ... AG42: =AF42+(AF42*AG40) -> 35000000
A44: MONTO CERTIFICADO | F44: =F38*F42 -> 0 | G44: =G38*G42 -> 0 | H44: =H38*H42 -> 0 | I44: =I38*I42 -> 0 | J44: =J38*J42 -> 0 | K44: =K38*K42 -> 0 | L44: =L38*L42 -> 0 | M44: =M38*M42 -> 0 | ... AG44: =AG38*AG42 -> 0
A46: MONTO A PAGAR (con descuento por adelanto) | F46: =F44-(F44*D4) -> 0 | G46: =G44-(G44*D4) -> 0 | H46: =H44-(H44*D4) -> 0 | I46: =I44-(I44*D4) -> 0 | J46: =J44-(J44*D4) -> 0 | K46: =K44-(K44*D4) -> 0 | L46: =L44-(L44*D4) -> 0 | M46: =M44-(M44*D4) -> 0 | N46: =N44-(N44*D4) -> 0 | O46: =O44-(O44*D4) -> 0 | P46: =P44-(P44*D4) -> 0 | Q46: =Q44-(Q44*D4) -> 0 | R46: =R44-(R44*D4) -> 0 | S46: =S44-(S44*D4) -> 0 | T46: =T44-(T44*D4) -> 0 | U46: =U44-(U44*D4) -> 0 | V46: =V44-(V44*D4) -> 0 | W46: =W44-(W44*D4) -> 0 | X46: =X44-(X44*D4) -> 0 | Y46: =Y44-(Y44*D4) -> 0 | Z46: =Z44-(Z44*D4) -> 0 | AA46: =AA44-(AA44*D4) -> 0 | AB46: =AB44-(AB44*D4) -> 0 | AC46: =AC44-(AC44*D4) -> 0 | AD46: =AD44-(AD44*D4) -> 0 | AE46: =AE44-(AE44*D4) -> 0 | AF46: =AF44-(AF44*D4) -> 0 | AG46: =AG44-(AG44*D4) -> 0
A48: SALDO DE OBRA ACTUALIZADO | F48: =F42-F46-C4 -> 35000000 | G48: =(F48+(F48*G40))-G46 -> 35000000 | H48: =(G48+(G48*H40))-H46 -> 35000000 | I48: =(H48+(H48*I40))-I46 -> 35000000 | J48: =(I48+(I48*J40))-J46 -> 35000000 | K48: =(J48+(J48*K40))-K46 -> 35000000 | L48: =(K48+(K48*L40))-L46 -> 35000000 | M48: =(L48+(L48*M40))-M46 -> 35000000 | N48: =(M48+(M48*N40))-N46 -> 35000000 | ... AG48: =(AF48+(AF48*AG40))-AG46 -> 35000000

Sheet M05
B1: SF - ALBAÑILERÍA BELTRÁN
A2: MES BASE ACTUALIZACIÓN | C2: 46113
A3: MONTO DE OBRA INICIAL | C3: 35000000
A4: ANTICIPO | C4: 0 | D4: =C4/C3 -> 0
F5: AGOSTO | H5: SEPTIEMBRE | J5: OCTUBRE | L5: NOVIEMBRE | N5: DICIEMBRE | P5: ENERO | R5: FEBRERO | T5: MARZO | V5: ABRIL | X5: MAYO | Z5: JUNIO | AB5: JULIO | AD5: AGOSTO | AF5: SEPTIEMBRE
A6: ITEM | B6: DESCRIPCIÓN | C6: % ITEM | D6: MONTO TOTAL | E6: FINALIZADO | F6: C1 | H6: C2 | J6: C3 | L6: C4 | N6: C5 | P6: C6 | R6: C7 | T6: C8 | V6: C9 | X6: C10 | Z6: C11 | AB6: C12 | AD6: C13 | AF6: C14
A7: 1 | B7: MAMPOSTERIA | C7: =SUM(C8:C9) -> 0.17 | D7: =C7*C3 -> 5950000 | F7: Q1 | G7: Q2 | H7: Q1 | I7: Q2 | J7: Q1 | K7: Q2 | L7: Q1 | M7: Q2 | N7: Q1 | O7: Q2 | P7: Q1 | Q7: Q2 | R7: Q1 | S7: Q2 | T7: Q1 | U7: Q2 | V7: Q1 | W7: Q2 | X7: Q1 | Y7: Q2 | Z7: Q3 | AA7: Q4 | AB7: Q5 | AC7: Q6 | AD7: Q7 | AE7: Q8 | AF7: Q9 | AG7: Q10
A8: 1 | B8: Módulo completo Brimax | C8: 0.12 | E8: =SUM(F8:AG8) -> 0
A9: 2 | B9: Contenciones de acceso a P.B. (Promedio 5m x 0,7h con viga de fundacion) | C9: 0.05 | E9: =SUM(F9:AG9) -> 0
A11: 2 | B11: REVOQUES | C11: =SUM(C12) -> 0.15 | D11: =C11*C3 -> 5250000
A12: 1 | B12: Módulo completo | C12: 0.15 | E12: =SUM(F12:AG12) -> 0
A14: 3 | B14: AISLACIONES | C14: =SUM(C15:C16) -> 0.12 | D14: =C14*C3 -> 4200000
A15: 1 | B15: Webertec (Exterior + duchas) | C15: 0.06 | E15: =SUM(F15:AG15) -> 0
A16: 2 | B16: Exterior (Memb. líquida - incluye cantero dormi) | C16: 0.06 | E16: =SUM(F16:AG16) -> 0
A18: 4 | B18: CONTRAPISOS | C18: =SUM(C19:C20) -> 0.18 | D18: =C18*C3 -> 6300000
A19: 1 | B19: Interior duplex | C19: 0.12 | E19: =SUM(F19:AG19) -> 0
A20: 2 | B20: Exterior | C20: 0.06 | E20: =SUM(F20:AG20) -> 0
A22: 5 | B22: CARPETAS | C22: =SUM(C23:C23) -> 0.06 | D22: =C22*C3 -> 2100000
A23: 1 | B23: Exterior | C23: 0.06 | E23: =SUM(F23:AG23) -> 0
A25: 6 | B25: HORMIGÓN | C25: =SUM(C26:C30) -> 0.16 | D25: =C25*C3 -> 5600000
A26: 1 | B26: Banco Tromen | C26: 0.05 | E26: =SUM(F26:AG26) -> 0
A27: 2 | B27: Parrilla | C27: 0.05 | E27: =SUM(F27:AG27) -> 0
A28: 3 | B28: Banquinas (Parrilla + bauleras) | C28: 0.02 | E28: =SUM(F28:AG28) -> 0
A29: 4 | B29: Losetones acceso vehicular | C29: 0.02 | E29: =SUM(F29:AG29) -> 0
A30: 5 | B30: Losetones acceso peatonal | C30: 0.02 | E30: =SUM(F30:AG30) -> 0
A32: 7 | B32: COLOCACIÓN | C32: =SUM(C33:C36) -> 0.16 | D32: =C32*C3 -> 5600000
A33: 1 | B33: Pisos | C33: 0.06 | E33: =SUM(F33:AG33) -> 0
A34: 2 | B34: Baños | C34: 0.06 | E34: =SUM(F34:AG34) -> 0
A35: 3 | B35: Cocina | C35: 0.03 | E35: =SUM(F35:AG35) -> 0
A36: 4 | B36: Refractarios parrilla | C36: 0.01 | E36: =SUM(F36:AG36) -> 0
B38: TOTAL OBRA | C38: =SUM(C7+C11+C14+C18+C22+C25+C32) -> 1 | E38: =SUM(F38:AG38) -> 0 | F38: =SUM(F8:F37) -> 0 | G38: =SUM(G8:G37) -> 0 | H38: =SUM(H8:H37) -> 0 | I38: =SUM(I8:I37) -> 0 | J38: =SUM(J8:J37) -> 0 | K38: =SUM(K8:K37) -> 0 | L38: =SUM(L8:L37) -> 0 | M38: =SUM(M8:M37) -> 0 | ... AG38: =SUM(AG8:AG37) -> 0
A40: AJUSTE | F40: 0 | G40: 0 | H40: 0 | I40: 0 | J40: 0 | K40: 0 | L40: 0 | M40: 0 | N40: 0 | O40: 0 | P40: 0 | Q40: 0 | R40: 0 | S40: 0 | T40: 0 | U40: 0 | V40: 0 | W40: 0 | X40: 0 | Y40: 0 | Z40: 0 | AA40: 0 | AB40: 0 | AC40: 0 | AD40: 0 | AE40: 0 | AF40: 0 | AG40: 0
A42: MONTO DE OBRA ACTUALIZADO | F42: =C3+(C3*F40) -> 35000000 | G42: =F42+(F42*G40) -> 35000000 | H42: =G42+(G42*H40) -> 35000000 | I42: =H42+(H42*I40) -> 35000000 | J42: =I42+(I42*J40) -> 35000000 | K42: =J42+(J42*K40) -> 35000000 | L42: =K42+(K42*L40) -> 35000000 | M42: =L42+(L42*M40) -> 35000000 | N42: =M42+(M42*N40) -> 35000000 | ... AG42: =AF42+(AF42*AG40) -> 35000000
A44: MONTO CERTIFICADO | F44: =F38*F42 -> 0 | G44: =G38*G42 -> 0 | H44: =H38*H42 -> 0 | I44: =I38*I42 -> 0 | J44: =J38*J42 -> 0 | K44: =K38*K42 -> 0 | L44: =L38*L42 -> 0 | M44: =M38*M42 -> 0 | ... AG44: =AG38*AG42 -> 0
A46: MONTO A PAGAR (con descuento por adelanto) | F46: =F44-(F44*D4) -> 0 | G46: =G44-(G44*D4) -> 0 | H46: =H44-(H44*D4) -> 0 | I46: =I44-(I44*D4) -> 0 | J46: =J44-(J44*D4) -> 0 | K46: =K44-(K44*D4) -> 0 | L46: =L44-(L44*D4) -> 0 | M46: =M44-(M44*D4) -> 0 | N46: =N44-(N44*D4) -> 0 | O46: =O44-(O44*D4) -> 0 | P46: =P44-(P44*D4) -> 0 | Q46: =Q44-(Q44*D4) -> 0 | R46: =R44-(R44*D4) -> 0 | S46: =S44-(S44*D4) -> 0 | T46: =T44-(T44*D4) -> 0 | U46: =U44-(U44*D4) -> 0 | V46: =V44-(V44*D4) -> 0 | W46: =W44-(W44*D4) -> 0 | X46: =X44-(X44*D4) -> 0 | Y46: =Y44-(Y44*D4) -> 0 | Z46: =Z44-(Z44*D4) -> 0 | AA46: =AA44-(AA44*D4) -> 0 | AB46: =AB44-(AB44*D4) -> 0 | AC46: =AC44-(AC44*D4) -> 0 | AD46: =AD44-(AD44*D4) -> 0 | AE46: =AE44-(AE44*D4) -> 0 | AF46: =AF44-(AF44*D4) -> 0 | AG46: =AG44-(AG44*D4) -> 0
A48: SALDO DE OBRA ACTUALIZADO | F48: =F42-F46-C4 -> 35000000 | G48: =(F48+(F48*G40))-G46 -> 35000000 | H48: =(G48+(G48*H40))-H46 -> 35000000 | I48: =(H48+(H48*I40))-I46 -> 35000000 | J48: =(I48+(I48*J40))-J46 -> 35000000 | K48: =(J48+(J48*K40))-K46 -> 35000000 | L48: =(K48+(K48*L40))-L46 -> 35000000 | M48: =(L48+(L48*M40))-M46 -> 35000000 | N48: =(M48+(M48*N40))-N46 -> 35000000 | ... AG48: =(AF48+(AF48*AG40))-AG46 -> 35000000

Sheet M04
B1: SF - ALBAÑILERÍA BELTRÁN
A2: MES BASE ACTUALIZACIÓN | C2: 46113
A3: MONTO DE OBRA INICIAL | C3: 35000000
A4: ANTICIPO | C4: 0 | D4: =C4/C3 -> 0
F5: NOVIEMBRE | H5: DICIEMBRE | J5: ENERO | L5: FEBRERO | N5: MARZO | P5: ABRIL | R5: MAYO | T5: JUNIO | V5: JULIO | X5: AGOSTO | Z5: SEPTIEMBRE | AB5: OCTUBRE | AD5: NOVIEMBRE | AF5: DICIEMBRE
A6: ITEM | B6: DESCRIPCIÓN | C6: % ITEM | D6: MONTO TOTAL | E6: FINALIZADO | F6: C1 | H6: C2 | J6: C3 | L6: C4 | N6: C5 | P6: C6 | R6: C7 | T6: C8 | V6: C9 | X6: C10 | Z6: C11 | AB6: C12 | AD6: C13 | AF6: C14
A7: 1 | B7: MAMPOSTERIA | C7: =SUM(C8:C9) -> 0.17 | D7: =C7*C3 -> 5950000 | F7: Q1 | G7: Q2 | H7: Q1 | I7: Q2 | J7: Q1 | K7: Q2 | L7: Q1 | M7: Q2 | N7: Q1 | O7: Q2 | P7: Q1 | Q7: Q2 | R7: Q1 | S7: Q2 | T7: Q1 | U7: Q2 | V7: Q1 | W7: Q2 | X7: Q1 | Y7: Q2 | Z7: Q3 | AA7: Q4 | AB7: Q5 | AC7: Q6 | AD7: Q7 | AE7: Q8 | AF7: Q9 | AG7: Q10
A8: 1 | B8: Módulo completo Brimax | C8: 0.12 | E8: =SUM(F8:AG8) -> 0
A9: 2 | B9: Contenciones de acceso a P.B. (Promedio 5m x 0,7h con viga de fundacion) | C9: 0.05 | E9: =SUM(F9:AG9) -> 0
A11: 2 | B11: REVOQUES | C11: =SUM(C12) -> 0.15 | D11: =C11*C3 -> 5250000
A12: 1 | B12: Módulo completo | C12: 0.15 | E12: =SUM(F12:AG12) -> 0
A14: 3 | B14: AISLACIONES | C14: =SUM(C15:C16) -> 0.12 | D14: =C14*C3 -> 4200000
A15: 1 | B15: Webertec (Exterior + duchas) | C15: 0.06 | E15: =SUM(F15:AG15) -> 0
A16: 2 | B16: Exterior (Memb. líquida - incluye cantero dormi) | C16: 0.06 | E16: =SUM(F16:AG16) -> 0
A18: 4 | B18: CONTRAPISOS | C18: =SUM(C19:C20) -> 0.18 | D18: =C18*C3 -> 6300000
A19: 1 | B19: Interior duplex | C19: 0.12 | E19: =SUM(F19:AG19) -> 0
A20: 2 | B20: Exterior | C20: 0.06 | E20: =SUM(F20:AG20) -> 0
A22: 5 | B22: CARPETAS | C22: =SUM(C23:C23) -> 0.06 | D22: =C22*C3 -> 2100000
A23: 1 | B23: Exterior | C23: 0.06 | E23: =SUM(F23:AG23) -> 0
A25: 6 | B25: HORMIGÓN | C25: =SUM(C26:C30) -> 0.16 | D25: =C25*C3 -> 5600000
A26: 1 | B26: Banco Tromen | C26: 0.05 | E26: =SUM(F26:AG26) -> 0
A27: 2 | B27: Parrilla | C27: 0.05 | E27: =SUM(F27:AG27) -> 0
A28: 3 | B28: Banquinas (Parrilla + bauleras) | C28: 0.02 | E28: =SUM(F28:AG28) -> 0
A29: 4 | B29: Losetones acceso vehicular | C29: 0.02 | E29: =SUM(F29:AG29) -> 0
A30: 5 | B30: Losetones acceso peatonal | C30: 0.02 | E30: =SUM(F30:AG30) -> 0
A32: 7 | B32: COLOCACIÓN | C32: =SUM(C33:C36) -> 0.16 | D32: =C32*C3 -> 5600000
A33: 1 | B33: Pisos | C33: 0.06 | E33: =SUM(F33:AG33) -> 0
A34: 2 | B34: Baños | C34: 0.06 | E34: =SUM(F34:AG34) -> 0
A35: 3 | B35: Cocina | C35: 0.03 | E35: =SUM(F35:AG35) -> 0
A36: 4 | B36: Refractarios parrilla | C36: 0.01 | E36: =SUM(F36:AG36) -> 0
B38: TOTAL OBRA | C38: =SUM(C7+C11+C14+C18+C22+C25+C32) -> 1 | E38: =SUM(F38:AG38) -> 0 | F38: =SUM(F8:F37) -> 0 | G38: =SUM(G8:G37) -> 0 | H38: =SUM(H8:H37) -> 0 | I38: =SUM(I8:I37) -> 0 | J38: =SUM(J8:J37) -> 0 | K38: =SUM(K8:K37) -> 0 | L38: =SUM(L8:L37) -> 0 | M38: =SUM(M8:M37) -> 0 | ... AG38: =SUM(AG8:AG37) -> 0
A40: AJUSTE | F40: 0 | G40: 0 | H40: 0 | I40: 0 | J40: 0 | K40: 0 | L40: 0 | M40: 0 | N40: 0 | O40: 0 | P40: 0 | Q40: 0 | R40: 0 | S40: 0 | T40: 0 | U40: 0 | V40: 0 | W40: 0 | X40: 0 | Y40: 0 | Z40: 0 | AA40: 0 | AB40: 0 | AC40: 0 | AD40: 0 | AE40: 0 | AF40: 0 | AG40: 0
A42: MONTO DE OBRA ACTUALIZADO | F42: =C3+(C3*F40) -> 35000000 | G42: =F42+(F42*G40) -> 35000000 | H42: =G42+(G42*H40) -> 35000000 | I42: =H42+(H42*I40) -> 35000000 | J42: =I42+(I42*J40) -> 35000000 | K42: =J42+(J42*K40) -> 35000000 | L42: =K42+(K42*L40) -> 35000000 | M42: =L42+(L42*M40) -> 35000000 | N42: =M42+(M42*N40) -> 35000000 | ... AG42: =AF42+(AF42*AG40) -> 35000000
A44: MONTO CERTIFICADO | F44: =F38*F42 -> 0 | G44: =G38*G42 -> 0 | H44: =H38*H42 -> 0 | I44: =I38*I42 -> 0 | J44: =J38*J42 -> 0 | K44: =K38*K42 -> 0 | L44: =L38*L42 -> 0 | M44: =M38*M42 -> 0 | ... AG44: =AG38*AG42 -> 0
A46: MONTO A PAGAR (con descuento por adelanto) | F46: =F44-(F44*D4) -> 0 | G46: =G44-(G44*D4) -> 0 | H46: =H44-(H44*D4) -> 0 | I46: =I44-(I44*D4) -> 0 | J46: =J44-(J44*D4) -> 0 | K46: =K44-(K44*D4) -> 0 | L46: =L44-(L44*D4) -> 0 | M46: =M44-(M44*D4) -> 0 | N46: =N44-(N44*D4) -> 0 | O46: =O44-(O44*D4) -> 0 | P46: =P44-(P44*D4) -> 0 | Q46: =Q44-(Q44*D4) -> 0 | R46: =R44-(R44*D4) -> 0 | S46: =S44-(S44*D4) -> 0 | T46: =T44-(T44*D4) -> 0 | U46: =U44-(U44*D4) -> 0 | V46: =V44-(V44*D4) -> 0 | W46: =W44-(W44*D4) -> 0 | X46: =X44-(X44*D4) -> 0 | Y46: =Y44-(Y44*D4) -> 0 | Z46: =Z44-(Z44*D4) -> 0 | AA46: =AA44-(AA44*D4) -> 0 | AB46: =AB44-(AB44*D4) -> 0 | AC46: =AC44-(AC44*D4) -> 0 | AD46: =AD44-(AD44*D4) -> 0 | AE46: =AE44-(AE44*D4) -> 0 | AF46: =AF44-(AF44*D4) -> 0 | AG46: =AG44-(AG44*D4) -> 0
A48: SALDO DE OBRA ACTUALIZADO | F48: =F42-F46-C4 -> 35000000 | G48: =(F48+(F48*G40))-G46 -> 35000000 | H48: =(G48+(G48*H40))-H46 -> 35000000 | I48: =(H48+(H48*I40))-I46 -> 35000000 | J48: =(I48+(I48*J40))-J46 -> 35000000 | K48: =(J48+(J48*K40))-K46 -> 35000000 | L48: =(K48+(K48*L40))-L46 -> 35000000 | M48: =(L48+(L48*M40))-M46 -> 35000000 | N48: =(M48+(M48*N40))-N46 -> 35000000 | ... AG48: =(AF48+(AF48*AG40))-AG46 -> 35000000

Sheet M13
B1: SF - ALBAÑILERÍA BELTRÁN
A2: MES BASE ACTUALIZACIÓN | C2: 46113
A3: MONTO DE OBRA INICIAL | C3: 35000000
A4: ANTICIPO | C4: 0 | D4: =C4/C3 -> 0
F5: NOVIEMBRE | H5: DICIEMBRE | J5: ENERO | L5: FEBRERO | N5: MARZO | P5: ABRIL | R5: MAYO | T5: JUNIO | V5: JULIO | X5: AGOSTO | Z5: SEPTIEMBRE | AB5: OCTUBRE | AD5: NOVIEMBRE | AF5: DICIEMBRE
A6: ITEM | B6: DESCRIPCIÓN | C6: % ITEM | D6: MONTO TOTAL | E6: FINALIZADO | F6: C1 | H6: C2 | J6: C3 | L6: C4 | N6: C5 | P6: C6 | R6: C7 | T6: C8 | V6: C9 | X6: C10 | Z6: C11 | AB6: C12 | AD6: C13 | AF6: C14
A7: 1 | B7: MAMPOSTERIA | C7: =SUM(C8:C9) -> 0.17 | D7: =C7*C3 -> 5950000 | F7: Q1 | G7: Q2 | H7: Q1 | I7: Q2 | J7: Q1 | K7: Q2 | L7: Q1 | M7: Q2 | N7: Q1 | O7: Q2 | P7: Q1 | Q7: Q2 | R7: Q1 | S7: Q2 | T7: Q1 | U7: Q2 | V7: Q1 | W7: Q2 | X7: Q1 | Y7: Q2 | Z7: Q3 | AA7: Q4 | AB7: Q5 | AC7: Q6 | AD7: Q7 | AE7: Q8 | AF7: Q9 | AG7: Q10
A8: 1 | B8: Módulo completo Brimax | C8: 0.12 | E8: =SUM(F8:AG8) -> 0
A9: 2 | B9: Contenciones de acceso a P.B. (Promedio 5m x 0,7h con viga de fundacion) | C9: 0.05 | E9: =SUM(F9:AG9) -> 0
A11: 2 | B11: REVOQUES | C11: =SUM(C12) -> 0.15 | D11: =C11*C3 -> 5250000
A12: 1 | B12: Módulo completo | C12: 0.15 | E12: =SUM(F12:AG12) -> 0
A14: 3 | B14: AISLACIONES | C14: =SUM(C15:C16) -> 0.12 | D14: =C14*C3 -> 4200000
A15: 1 | B15: Webertec (Exterior + duchas) | C15: 0.06 | E15: =SUM(F15:AG15) -> 0
A16: 2 | B16: Exterior (Memb. líquida - incluye cantero dormi) | C16: 0.06 | E16: =SUM(F16:AG16) -> 0
A18: 4 | B18: CONTRAPISOS | C18: =SUM(C19:C20) -> 0.18 | D18: =C18*C3 -> 6300000
A19: 1 | B19: Interior duplex | C19: 0.12 | E19: =SUM(F19:AG19) -> 0
A20: 2 | B20: Exterior | C20: 0.06 | E20: =SUM(F20:AG20) -> 0
A22: 5 | B22: CARPETAS | C22: =SUM(C23:C23) -> 0.06 | D22: =C22*C3 -> 2100000
A23: 1 | B23: Exterior | C23: 0.06 | E23: =SUM(F23:AG23) -> 0
A25: 6 | B25: HORMIGÓN | C25: =SUM(C26:C30) -> 0.16 | D25: =C25*C3 -> 5600000
A26: 1 | B26: Banco Tromen | C26: 0.05 | E26: =SUM(F26:AG26) -> 0
A27: 2 | B27: Parrilla | C27: 0.05 | E27: =SUM(F27:AG27) -> 0
A28: 3 | B28: Banquinas (Parrilla + bauleras) | C28: 0.02 | E28: =SUM(F28:AG28) -> 0
A29: 4 | B29: Losetones acceso vehicular | C29: 0.02 | E29: =SUM(F29:AG29) -> 0
A30: 5 | B30: Losetones acceso peatonal | C30: 0.02 | E30: =SUM(F30:AG30) -> 0
A32: 7 | B32: COLOCACIÓN | C32: =SUM(C33:C36) -> 0.16 | D32: =C32*C3 -> 5600000
A33: 1 | B33: Pisos | C33: 0.06 | E33: =SUM(F33:AG33) -> 0
A34: 2 | B34: Baños | C34: 0.06 | E34: =SUM(F34:AG34) -> 0
A35: 3 | B35: Cocina | C35: 0.03 | E35: =SUM(F35:AG35) -> 0
A36: 4 | B36: Refractarios parrilla | C36: 0.01 | E36: =SUM(F36:AG36) -> 0
B38: TOTAL OBRA | C38: =SUM(C7+C11+C14+C18+C22+C25+C32) -> 1 | E38: =SUM(F38:AG38) -> 0 | F38: =SUM(F8:F37) -> 0 | G38: =SUM(G8:G37) -> 0 | H38: =SUM(H8:H37) -> 0 | I38: =SUM(I8:I37) -> 0 | J38: =SUM(J8:J37) -> 0 | K38: =SUM(K8:K37) -> 0 | L38: =SUM(L8:L37) -> 0 | M38: =SUM(M8:M37) -> 0 | ... AG38: =SUM(AG8:AG37) -> 0
A40: AJUSTE | F40: 0 | G40: 0 | H40: 0 | I40: 0 | J40: 0 | K40: 0 | L40: 0 | M40: 0 | N40: 0 | O40: 0 | P40: 0 | Q40: 0 | R40: 0 | S40: 0 | T40: 0 | U40: 0 | V40: 0 | W40: 0 | X40: 0 | Y40: 0 | Z40: 0 | AA40: 0 | AB40: 0 | AC40: 0 | AD40: 0 | AE40: 0 | AF40: 0 | AG40: 0
A42: MONTO DE OBRA ACTUALIZADO | F42: =C3+(C3*F40) -> 35000000 | G42: =F42+(F42*G40) -> 35000000 | H42: =G42+(G42*H40) -> 35000000 | I42: =H42+(H42*I40) -> 35000000 | J42: =I42+(I42*J40) -> 35000000 | K42: =J42+(J42*K40) -> 35000000 | L42: =K42+(K42*L40) -> 35000000 | M42: =L42+(L42*M40) -> 35000000 | N42: =M42+(M42*N40) -> 35000000 | ... AG42: =AF42+(AF42*AG40) -> 35000000
A44: MONTO CERTIFICADO | F44: =F38*F42 -> 0 | G44: =G38*G42 -> 0 | H44: =H38*H42 -> 0 | I44: =I38*I42 -> 0 | J44: =J38*J42 -> 0 | K44: =K38*K42 -> 0 | L44: =L38*L42 -> 0 | M44: =M38*M42 -> 0 | ... AG44: =AG38*AG42 -> 0
A46: MONTO A PAGAR (con descuento por adelanto) | F46: =F44-(F44*D4) -> 0 | G46: =G44-(G44*D4) -> 0 | H46: =H44-(H44*D4) -> 0 | I46: =I44-(I44*D4) -> 0 | J46: =J44-(J44*D4) -> 0 | K46: =K44-(K44*D4) -> 0 | L46: =L44-(L44*D4) -> 0 | M46: =M44-(M44*D4) -> 0 | N46: =N44-(N44*D4) -> 0 | O46: =O44-(O44*D4) -> 0 | P46: =P44-(P44*D4) -> 0 | Q46: =Q44-(Q44*D4) -> 0 | R46: =R44-(R44*D4) -> 0 | S46: =S44-(S44*D4) -> 0 | T46: =T44-(T44*D4) -> 0 | U46: =U44-(U44*D4) -> 0 | V46: =V44-(V44*D4) -> 0 | W46: =W44-(W44*D4) -> 0 | X46: =X44-(X44*D4) -> 0 | Y46: =Y44-(Y44*D4) -> 0 | Z46: =Z44-(Z44*D4) -> 0 | AA46: =AA44-(AA44*D4) -> 0 | AB46: =AB44-(AB44*D4) -> 0 | AC46: =AC44-(AC44*D4) -> 0 | AD46: =AD44-(AD44*D4) -> 0 | AE46: =AE44-(AE44*D4) -> 0 | AF46: =AF44-(AF44*D4) -> 0 | AG46: =AG44-(AG44*D4) -> 0
A48: SALDO DE OBRA ACTUALIZADO | F48: =F42-F46-C4 -> 35000000 | G48: =(F48+(F48*G40))-G46 -> 35000000 | H48: =(G48+(G48*H40))-H46 -> 35000000 | I48: =(H48+(H48*I40))-I46 -> 35000000 | J48: =(I48+(I48*J40))-J46 -> 35000000 | K48: =(J48+(J48*K40))-K46 -> 35000000 | L48: =(K48+(K48*L40))-L46 -> 35000000 | M48: =(L48+(L48*M40))-M46 -> 35000000 | N48: =(M48+(M48*N40))-N46 -> 35000000 | ... AG48: =(AF48+(AF48*AG40))-AG46 -> 35000000

Sheet M02
B1: SF - ALBAÑILERÍA BELTRÁN
A2: MES BASE ACTUALIZACIÓN | C2: 46113
A3: MONTO DE OBRA INICIAL | C3: 35000000
A4: ANTICIPO | C4: 0 | D4: =C4/C3 -> 0
F5: FEBRERO | H5: MARZO | J5: ABRIL | L5: MAYO | N5: JUNIO | P5: JULIO | R5: AGOSTO | T5: SEPTIEMBRE | V5: OCTUBRE | X5: NOVIEMBRE | Z5: DICIEMBRE | AB5: ENERO | AD5: FEBRERO | AF5: MARZO
A6: ITEM | B6: DESCRIPCIÓN | C6: % ITEM | D6: MONTO TOTAL | E6: FINALIZADO | F6: C1 | H6: C2 | J6: C3 | L6: C4 | N6: C5 | P6: C6 | R6: C7 | T6: C8 | V6: C9 | X6: C10 | Z6: C11 | AB6: C12 | AD6: C13 | AF6: C14
A7: 1 | B7: MAMPOSTERIA | C7: =SUM(C8:C9) -> 0.17 | D7: =C7*C3 -> 5950000 | F7: Q1 | G7: Q2 | H7: Q1 | I7: Q2 | J7: Q1 | K7: Q2 | L7: Q1 | M7: Q2 | N7: Q1 | O7: Q2 | P7: Q1 | Q7: Q2 | R7: Q1 | S7: Q2 | T7: Q1 | U7: Q2 | V7: Q1 | W7: Q2 | X7: Q1 | Y7: Q2 | Z7: Q3 | AA7: Q4 | AB7: Q5 | AC7: Q6 | AD7: Q7 | AE7: Q8 | AF7: Q9 | AG7: Q10
A8: 1 | B8: Módulo completo Brimax | C8: 0.12 | E8: =SUM(F8:AG8) -> 0
A9: 2 | B9: Contenciones de acceso a P.B. (Promedio 5m x 0,7h con viga de fundacion) | C9: 0.05 | E9: =SUM(F9:AG9) -> 0
A11: 2 | B11: REVOQUES | C11: =SUM(C12) -> 0.15 | D11: =C11*C3 -> 5250000
A12: 1 | B12: Módulo completo | C12: 0.15 | E12: =SUM(F12:AG12) -> 0
A14: 3 | B14: AISLACIONES | C14: =SUM(C15:C16) -> 0.12 | D14: =C14*C3 -> 4200000
A15: 1 | B15: Webertec (Exterior + duchas) | C15: 0.06 | E15: =SUM(F15:AG15) -> 0
A16: 2 | B16: Exterior (Memb. líquida - incluye cantero dormi) | C16: 0.06 | E16: =SUM(F16:AG16) -> 0
A18: 4 | B18: CONTRAPISOS | C18: =SUM(C19:C20) -> 0.18 | D18: =C18*C3 -> 6300000
A19: 1 | B19: Interior duplex | C19: 0.12 | E19: =SUM(F19:AG19) -> 0
A20: 2 | B20: Exterior | C20: 0.06 | E20: =SUM(F20:AG20) -> 0
A22: 5 | B22: CARPETAS | C22: =SUM(C23:C23) -> 0.06 | D22: =C22*C3 -> 2100000
A23: 1 | B23: Exterior | C23: 0.06 | E23: =SUM(F23:AG23) -> 0
A25: 6 | B25: HORMIGÓN | C25: =SUM(C26:C30) -> 0.16 | D25: =C25*C3 -> 5600000
A26: 1 | B26: Banco Tromen | C26: 0.05 | E26: =SUM(F26:AG26) -> 0
A27: 2 | B27: Parrilla | C27: 0.05 | E27: =SUM(F27:AG27) -> 0
A28: 3 | B28: Banquinas (Parrilla + bauleras) | C28: 0.02 | E28: =SUM(F28:AG28) -> 0
A29: 4 | B29: Losetones acceso vehicular | C29: 0.02 | E29: =SUM(F29:AG29) -> 0
A30: 5 | B30: Losetones acceso peatonal | C30: 0.02 | E30: =SUM(F30:AG30) -> 0
A32: 7 | B32: COLOCACIÓN | C32: =SUM(C33:C36) -> 0.16 | D32: =C32*C3 -> 5600000
A33: 1 | B33: Pisos | C33: 0.06 | E33: =SUM(F33:AG33) -> 0
A34: 2 | B34: Baños | C34: 0.06 | E34: =SUM(F34:AG34) -> 0
A35: 3 | B35: Cocina | C35: 0.03 | E35: =SUM(F35:AG35) -> 0
A36: 4 | B36: Refractarios parrilla | C36: 0.01 | E36: =SUM(F36:AG36) -> 0
B38: TOTAL OBRA | C38: =SUM(C7+C11+C14+C18+C22+C25+C32) -> 1 | E38: =SUM(F38:AG38) -> 0 | F38: =SUM(F8:F37) -> 0 | G38: =SUM(G8:G37) -> 0 | H38: =SUM(H8:H37) -> 0 | I38: =SUM(I8:I37) -> 0 | J38: =SUM(J8:J37) -> 0 | K38: =SUM(K8:K37) -> 0 | L38: =SUM(L8:L37) -> 0 | M38: =SUM(M8:M37) -> 0 | ... AG38: =SUM(AG8:AG37) -> 0
A40: AJUSTE | F40: 0 | G40: 0 | H40: 0 | I40: 0 | J40: 0 | K40: 0 | L40: 0 | M40: 0 | N40: 0 | O40: 0 | P40: 0 | Q40: 0 | R40: 0 | S40: 0 | T40: 0 | U40: 0 | V40: 0 | W40: 0 | X40: 0 | Y40: 0 | Z40: 0 | AA40: 0 | AB40: 0 | AC40: 0 | AD40: 0 | AE40: 0 | AF40: 0 | AG40: 0
A42: MONTO DE OBRA ACTUALIZADO | F42: =C3+(C3*F40) -> 35000000 | G42: =F42+(F42*G40) -> 35000000 | H42: =G42+(G42*H40) -> 35000000 | I42: =H42+(H42*I40) -> 35000000 | J42: =I42+(I42*J40) -> 35000000 | K42: =J42+(J42*K40) -> 35000000 | L42: =K42+(K42*L40) -> 35000000 | M42: =L42+(L42*M40) -> 35000000 | N42: =M42+(M42*N40) -> 35000000 | ... AG42: =AF42+(AF42*AG40) -> 35000000
A44: MONTO CERTIFICADO | F44: =F38*F42 -> 0 | G44: =G38*G42 -> 0 | H44: =H38*H42 -> 0 | I44: =I38*I42 -> 0 | J44: =J38*J42 -> 0 | K44: =K38*K42 -> 0 | L44: =L38*L42 -> 0 | M44: =M38*M42 -> 0 | ... AG44: =AG38*AG42 -> 0
A46: MONTO A PAGAR (con descuento por adelanto) | F46: =F44-(F44*D4) -> 0 | G46: =G44-(G44*D4) -> 0 | H46: =H44-(H44*D4) -> 0 | I46: =I44-(I44*D4) -> 0 | J46: =J44-(J44*D4) -> 0 | K46: =K44-(K44*D4) -> 0 | L46: =L44-(L44*D4) -> 0 | M46: =M44-(M44*D4) -> 0 | N46: =N44-(N44*D4) -> 0 | O46: =O44-(O44*D4) -> 0 | P46: =P44-(P44*D4) -> 0 | Q46: =Q44-(Q44*D4) -> 0 | R46: =R44-(R44*D4) -> 0 | S46: =S44-(S44*D4) -> 0 | T46: =T44-(T44*D4) -> 0 | U46: =U44-(U44*D4) -> 0 | V46: =V44-(V44*D4) -> 0 | W46: =W44-(W44*D4) -> 0 | X46: =X44-(X44*D4) -> 0 | Y46: =Y44-(Y44*D4) -> 0 | Z46: =Z44-(Z44*D4) -> 0 | AA46: =AA44-(AA44*D4) -> 0 | AB46: =AB44-(AB44*D4) -> 0 | AC46: =AC44-(AC44*D4) -> 0 | AD46: =AD44-(AD44*D4) -> 0 | AE46: =AE44-(AE44*D4) -> 0 | AF46: =AF44-(AF44*D4) -> 0 | AG46: =AG44-(AG44*D4) -> 0
A48: SALDO DE OBRA ACTUALIZADO | F48: =F42-F46-C4 -> 35000000 | G48: =(F48+(F48*G40))-G46 -> 35000000 | H48: =(G48+(G48*H40))-H46 -> 35000000 | I48: =(H48+(H48*I40))-I46 -> 35000000 | J48: =(I48+(I48*J40))-J46 -> 35000000 | K48: =(J48+(J48*K40))-K46 -> 35000000 | L48: =(K48+(K48*L40))-L46 -> 35000000 | M48: =(L48+(L48*M40))-M46 -> 35000000 | N48: =(M48+(M48*N40))-N46 -> 35000000 | ... AG48: =(AF48+(AF48*AG40))-AG46 -> 35000000
